LICENSE
consoler/__init__.py
consoler/colours.py
consoler/console.py
consoler/settings.py
consoler-0.1.7.dist-info/LICENSE
consoler-0.1.7.dist-info/METADATA
consoler-0.1.7.dist-info/WHEEL
consoler-0.1.7.dist-info/RECORD
