Metadata-Version: 2.1
Name: consoler
Version: 0.1.7
Summary: 
Home-page: https://github.com/hactar-is/consoler
License: MIT
Keywords: console,terminal,logging
Author: Hactar
Author-email: systems@hactar.is
Requires-Python: >=3.6,<4.0
Classifier: Environment :: Console
Classifier: License :: OSI Approved :: MIT License
Classifier: Operating System :: OS Independent
Classifier: Programming Language :: Python :: 3
Classifier: Programming Language :: Python :: 3.6
Classifier: Programming Language :: Python :: 3.7
Classifier: Programming Language :: Python :: 3.8
Classifier: Programming Language :: Python :: 3.9
Classifier: Programming Language :: Python :: 3.10
Classifier: Programming Language :: Python :: 3.11
Classifier: Programming Language :: Python :: 3.12
Classifier: Topic :: Software Development :: Libraries :: Python Modules
Requires-Dist: arrow (>=1.2.3,<2.0.0)
Project-URL: Repository, https://github.com/hactar-is/consoler
